{
  "width": 500,
  "height": 350,
  "padding": {
    "top": 10,
    "left": 50,
    "bottom": 30,
    "right": 10
  },
  "data": [
    {
      "name": "wymulrjs",
      "values": [
        {
          "x": 0,
          "y": 0.016615608287034633
        },
        {
          "x": 1,
          "y": 0.09517628121917025
        },
        {
          "x": 2,
          "y": 0.0
        },
        {
          "x": 3,
          "y": 0.0
        },
        {
          "x": 4,
          "y": 0.32493898956332107
        },
        {
          "x": 5,
          "y": 0.0
        },
        {
          "x": 6,
          "y": 0.0
        },
        {
          "x": 7,
          "y": 0.0
        },
        {
          "x": 8,
          "y": 0.0
        },
        {
          "x": 9,
          "y": 0.0
        },
        {
          "x": 10,
          "y": 0.0
        },
        {
          "x": 11,
          "y": 0.0
        },
        {
          "x": 12,
          "y": 0.7177423542239991
        },
        {
          "x": 13,
          "y": 0.0
        },
        {
          "x": 14,
          "y": 0.0
        },
        {
          "x": 15,
          "y": 0.0
        },
        {
          "x": 16,
          "y": 0.0
        },
        {
          "x": 17,
          "y": 0.0
        },
        {
          "x": 18,
          "y": 0.0
        },
        {
          "x": 19,
          "y": 0.0
        },
        {
          "x": 20,
          "y": 0.0
        },
        {
          "x": 21,
          "y": 0.0
        },
        {
          "x": 22,
          "y": 1.0
        },
        {
          "x": 23,
          "y": 0.0
        },
        {
          "x": 24,
          "y": 0.0
        },
        {
          "x": 25,
          "y": 0.0
        },
        {
          "x": 26,
          "y": 0.0
        },
        {
          "x": 27,
          "y": 0.0
        },
        {
          "x": 28,
          "y": 0.0
        },
        {
          "x": 29,
          "y": 0.0
        },
        {
          "x": 30,
          "y": 0.0
        },
        {
          "x": 31,
          "y": 0.0
        },
        {
          "x": 32,
          "y": 0.9532166779168181
        },
        {
          "x": 33,
          "y": 0.0
        },
        {
          "x": 34,
          "y": 0.0
        },
        {
          "x": 35,
          "y": 0.0
        },
        {
          "x": 36,
          "y": 0.0
        },
        {
          "x": 37,
          "y": 0.0
        },
        {
          "x": 38,
          "y": 0.0
        },
        {
          "x": 39,
          "y": 0.0
        },
        {
          "x": 40,
          "y": 0.8505114491925854
        },
        {
          "x": 41,
          "y": 0.0
        },
        {
          "x": 42,
          "y": 0.0
        },
        {
          "x": 43,
          "y": 0.0
        },
        {
          "x": 44,
          "y": 0.0
        },
        {
          "x": 45,
          "y": 0.0
        },
        {
          "x": 46,
          "y": 0.0
        },
        {
          "x": 47,
          "y": 0.0
        },
        {
          "x": 48,
          "y": 0.0
        },
        {
          "x": 49,
          "y": 0.0
        },
        {
          "x": 50,
          "y": 0.8948543538086089
        },
        {
          "x": 51,
          "y": 0.0
        },
        {
          "x": 52,
          "y": 0.0
        },
        {
          "x": 53,
          "y": 0.0
        },
        {
          "x": 54,
          "y": 0.0
        },
        {
          "x": 55,
          "y": 0.0
        },
        {
          "x": 56,
          "y": 0.0
        },
        {
          "x": 57,
          "y": 0.0
        },
        {
          "x": 58,
          "y": 0.0
        },
        {
          "x": 59,
          "y": 0.0
        },
        {
          "x": 60,
          "y": 0.9772054623812243
        },
        {
          "x": 61,
          "y": 0.0
        },
        {
          "x": 62,
          "y": 0.0
        },
        {
          "x": 63,
          "y": 0.0
        },
        {
          "x": 64,
          "y": 0.0
        },
        {
          "x": 65,
          "y": 0.0
        },
        {
          "x": 66,
          "y": 0.0
        },
        {
          "x": 67,
          "y": 0.0
        },
        {
          "x": 68,
          "y": 0.0
        },
        {
          "x": 69,
          "y": 0.906692974713121
        },
        {
          "x": 70,
          "y": 0.0
        },
        {
          "x": 71,
          "y": 0.0
        },
        {
          "x": 72,
          "y": 0.0
        },
        {
          "x": 73,
          "y": 0.0
        },
        {
          "x": 74,
          "y": 0.0
        },
        {
          "x": 75,
          "y": 0.0
        },
        {
          "x": 76,
          "y": 0.0
        },
        {
          "x": 77,
          "y": 0.8345189262163143
        },
        {
          "x": 78,
          "y": 0.0
        },
        {
          "x": 79,
          "y": 0.0
        },
        {
          "x": 80,
          "y": 0.0
        },
        {
          "x": 81,
          "y": 0.0
        },
        {
          "x": 82,
          "y": 0.0
        },
        {
          "x": 83,
          "y": 0.0
        },
        {
          "x": 84,
          "y": 0.0
        },
        {
          "x": 85,
          "y": 0.0
        },
        {
          "x": 86,
          "y": 0.7965107222597226
        },
        {
          "x": 87,
          "y": 0.0
        },
        {
          "x": 88,
          "y": 0.0
        },
        {
          "x": 89,
          "y": 0.0
        },
        {
          "x": 90,
          "y": 0.0
        },
        {
          "x": 91,
          "y": 0.0
        },
        {
          "x": 92,
          "y": 0.0
        },
        {
          "x": 93,
          "y": 0.0
        },
        {
          "x": 94,
          "y": 0.7877875279090296
        },
        {
          "x": 95,
          "y": 0.0
        },
        {
          "x": 96,
          "y": 0.0
        },
        {
          "x": 97,
          "y": 0.0
        },
        {
          "x": 98,
          "y": 0.0
        },
        {
          "x": 99,
          "y": 0.0
        },
        {
          "x": 100,
          "y": 0.0
        },
        {
          "x": 101,
          "y": 0.0
        },
        {
          "x": 102,
          "y": 0.7887221558751751
        },
        {
          "x": 103,
          "y": 0.0
        },
        {
          "x": 104,
          "y": 0.0
        },
        {
          "x": 105,
          "y": 0.0
        },
        {
          "x": 106,
          "y": 0.0
        },
        {
          "x": 107,
          "y": 0.0
        },
        {
          "x": 108,
          "y": 0.0
        },
        {
          "x": 109,
          "y": 0.7561659483877667
        },
        {
          "x": 110,
          "y": 0.0
        },
        {
          "x": 111,
          "y": 0.0
        },
        {
          "x": 112,
          "y": 0.0
        },
        {
          "x": 113,
          "y": 0.0
        },
        {
          "x": 114,
          "y": 0.0
        },
        {
          "x": 115,
          "y": 0.0
        },
        {
          "x": 116,
          "y": 0.0
        },
        {
          "x": 117,
          "y": 0.7485331533309102
        },
        {
          "x": 118,
          "y": 0.0
        },
        {
          "x": 119,
          "y": 0.0
        },
        {
          "x": 120,
          "y": 0.0
        },
        {
          "x": 121,
          "y": 0.0
        },
        {
          "x": 122,
          "y": 0.0
        },
        {
          "x": 123,
          "y": 0.0
        },
        {
          "x": 124,
          "y": 0.0
        },
        {
          "x": 125,
          "y": 0.7480658393478373
        },
        {
          "x": 126,
          "y": 0.0
        },
        {
          "x": 127,
          "y": 0.0
        },
        {
          "x": 128,
          "y": 0.0
        },
        {
          "x": 129,
          "y": 0.0
        },
        {
          "x": 130,
          "y": 0.0
        },
        {
          "x": 131,
          "y": 0.0
        },
        {
          "x": 132,
          "y": 0.7175865828963082
        },
        {
          "x": 133,
          "y": 0.0
        },
        {
          "x": 134,
          "y": 0.0
        },
        {
          "x": 135,
          "y": 0.0
        },
        {
          "x": 136,
          "y": 0.0
        },
        {
          "x": 137,
          "y": 0.0
        },
        {
          "x": 138,
          "y": 0.0
        },
        {
          "x": 139,
          "y": 0.6695051664157018
        },
        {
          "x": 140,
          "y": 0.0
        },
        {
          "x": 141,
          "y": 0.0
        },
        {
          "x": 142,
          "y": 0.0
        },
        {
          "x": 143,
          "y": 0.0
        },
        {
          "x": 144,
          "y": 0.0
        },
        {
          "x": 145,
          "y": 0.5820136040292849
        },
        {
          "x": 146,
          "y": 0.0
        },
        {
          "x": 147,
          "y": 0.0
        },
        {
          "x": 148,
          "y": 0.0
        },
        {
          "x": 149,
          "y": 0.0
        },
        {
          "x": 150,
          "y": 0.5104107170673451
        },
        {
          "x": 151,
          "y": 0.0
        },
        {
          "x": 152,
          "y": 0.0
        },
        {
          "x": 153,
          "y": 0.0
        },
        {
          "x": 154,
          "y": 0.0
        },
        {
          "x": 155,
          "y": 0.45235993561451787
        },
        {
          "x": 156,
          "y": 0.0
        },
        {
          "x": 157,
          "y": 0.0
        },
        {
          "x": 158,
          "y": 0.0
        },
        {
          "x": 159,
          "y": 0.4188691001609636
        },
        {
          "x": 160,
          "y": 0.0
        },
        {
          "x": 161,
          "y": 0.0
        },
        {
          "x": 162,
          "y": 0.0
        },
        {
          "x": 163,
          "y": 0.3947245443688665
        },
        {
          "x": 164,
          "y": 0.0
        },
        {
          "x": 165,
          "y": 0.0
        },
        {
          "x": 166,
          "y": 0.0
        },
        {
          "x": 167,
          "y": 0.37681084168440726
        },
        {
          "x": 168,
          "y": 0.0
        },
        {
          "x": 169,
          "y": 0.0
        },
        {
          "x": 170,
          "y": 0.0
        },
        {
          "x": 171,
          "y": 0.34695467054364193
        },
        {
          "x": 172,
          "y": 0.0
        },
        {
          "x": 173,
          "y": 0.0
        },
        {
          "x": 174,
          "y": 0.334285269224778
        },
        {
          "x": 175,
          "y": 0.0
        },
        {
          "x": 176,
          "y": 0.0
        },
        {
          "x": 177,
          "y": 0.30385793654914584
        },
        {
          "x": 178,
          "y": 0.0
        },
        {
          "x": 179,
          "y": 0.0
        },
        {
          "x": 180,
          "y": 0.2990290253907264
        },
        {
          "x": 181,
          "y": 0.0
        },
        {
          "x": 182,
          "y": 0.0
        },
        {
          "x": 183,
          "y": 0.2749363933745262
        },
        {
          "x": 184,
          "y": 0.0
        },
        {
          "x": 185,
          "y": 0.0
        },
        {
          "x": 186,
          "y": 0.2636170102289839
        },
        {
          "x": 187,
          "y": 0.0
        },
        {
          "x": 188,
          "y": 0.24663793551067031
        },
        {
          "x": 189,
          "y": 0.0
        },
        {
          "x": 190,
          "y": 0.0
        },
        {
          "x": 191,
          "y": 0.23235889713899993
        },
        {
          "x": 192,
          "y": 0.0
        },
        {
          "x": 193,
          "y": 0.22249337971857314
        },
        {
          "x": 194,
          "y": 0.0
        },
        {
          "x": 195,
          "y": 0.21247209097045536
        },
        {
          "x": 196,
          "y": 0.0
        },
        {
          "x": 197,
          "y": 0.2090451217612545
        },
        {
          "x": 198,
          "y": 0.0
        },
        {
          "x": 199,
          "y": 0.19388337919933538
        },
        {
          "x": 200,
          "y": 0.0
        },
        {
          "x": 201,
          "y": 0.1804870450179137
        },
        {
          "x": 202,
          "y": 0.0
        },
        {
          "x": 203,
          "y": 0.17602160029077316
        },
        {
          "x": 204,
          "y": 0.15675787943299238
        },
        {
          "x": 205,
          "y": 0.0
        },
        {
          "x": 206,
          "y": 0.15333091022379147
        },
        {
          "x": 207,
          "y": 0.14310192637208577
        },
        {
          "x": 208,
          "y": 0.0
        },
        {
          "x": 209,
          "y": 0.13806532011007838
        },
        {
          "x": 210,
          "y": 0.13375564671062878
        },
        {
          "x": 211,
          "y": 0.12601900410197828
        },
        {
          "x": 212,
          "y": 0.0
        },
        {
          "x": 213,
          "y": 0.12435744327327483
        },
        {
          "x": 214,
          "y": 0.12020354120151616
        },
        {
          "x": 215,
          "y": 0.11703619087180019
        },
        {
          "x": 216,
          "y": 0.11033802378108935
        },
        {
          "x": 217,
          "y": 0.102185990965263
        },
        {
          "x": 218,
          "y": 0.0965782231683888
        },
        {
          "x": 219,
          "y": 0.092891635079703
        },
        {
          "x": 220,
          "y": 0.09387818682174567
        },
        {
          "x": 221,
          "y": 0.08889350433563528
        },
        {
          "x": 222,
          "y": 0.08583000155771328
        },
        {
          "x": 223,
          "y": 0.08297419388337919
        },
        {
          "x": 224,
          "y": 0.15395399553455527
        },
        {
          "x": 225,
          "y": 0.07310867646295238
        },
        {
          "x": 226,
          "y": 0.07170673451373384
        },
        {
          "x": 227,
          "y": 0.1316267718988525
        },
        {
          "x": 228,
          "y": 0.1160496391297575
        },
        {
          "x": 229,
          "y": 0.05405265070875954
        },
        {
          "x": 230,
          "y": 0.10166675320629316
        },
        {
          "x": 231,
          "y": 0.14154421309517629
        },
        {
          "x": 232,
          "y": 0.09252816864842411
        },
        {
          "x": 233,
          "y": 0.0937743392699517
        },
        {
          "x": 234,
          "y": 0.08333766031465807
        },
        {
          "x": 235,
          "y": 0.10872838672828287
        },
        {
          "x": 236,
          "y": 0.09128199802689652
        },
        {
          "x": 237,
          "y": 0.105249493743185
        },
        {
          "x": 238,
          "y": 0.0965782231683888
        },
        {
          "x": 239,
          "y": 0.10628796926112466
        },
        {
          "x": 240,
          "y": 0.08401266940131887
        },
        {
          "x": 241,
          "y": 0.10514564619139104
        },
        {
          "x": 242,
          "y": 0.09585129030583103
        },
        {
          "x": 243,
          "y": 0.11090918531595617
        },
        {
          "x": 244,
          "y": 0.08972428474998702
        },
        {
          "x": 245,
          "y": 0.10291292382782075
        },
        {
          "x": 246,
          "y": 0.09045121761254478
        },
        {
          "x": 247,
          "y": 0.09709746092735863
        },
        {
          "x": 248,
          "y": 0.09455319590840645
        },
        {
          "x": 249,
          "y": 0.10929954826314969
        },
        {
          "x": 250,
          "y": 0.08318188898696713
        },
        {
          "x": 251,
          "y": 0.11272651747235057
        },
        {
          "x": 252,
          "y": 0.09787631756581339
        },
        {
          "x": 253,
          "y": 0.09673399449607975
        },
        {
          "x": 254,
          "y": 0.09958980217041383
        },
        {
          "x": 255,
          "y": 0.05005451996469183
        }
      ]
    },
    {
      "name": "maoyjwri",
      "values": [
        {
          "x": 0,
          "y": 0.0006666666666666666
        },
        {
          "x": 1,
          "y": 0.004485416666666667
        },
        {
          "x": 2,
          "y": 0.004485416666666667
        },
        {
          "x": 3,
          "y": 0.004485416666666667
        },
        {
          "x": 4,
          "y": 0.017522916666666666
        },
        {
          "x": 5,
          "y": 0.017522916666666666
        },
        {
          "x": 6,
          "y": 0.017522916666666666
        },
        {
          "x": 7,
          "y": 0.017522916666666666
        },
        {
          "x": 8,
          "y": 0.017522916666666666
        },
        {
          "x": 9,
          "y": 0.017522916666666666
        },
        {
          "x": 10,
          "y": 0.017522916666666666
        },
        {
          "x": 11,
          "y": 0.017522916666666666
        },
        {
          "x": 12,
          "y": 0.04632083333333333
        },
        {
          "x": 13,
          "y": 0.04632083333333333
        },
        {
          "x": 14,
          "y": 0.04632083333333333
        },
        {
          "x": 15,
          "y": 0.04632083333333333
        },
        {
          "x": 16,
          "y": 0.04632083333333333
        },
        {
          "x": 17,
          "y": 0.04632083333333333
        },
        {
          "x": 18,
          "y": 0.04632083333333333
        },
        {
          "x": 19,
          "y": 0.04632083333333333
        },
        {
          "x": 20,
          "y": 0.04632083333333333
        },
        {
          "x": 21,
          "y": 0.04632083333333333
        },
        {
          "x": 22,
          "y": 0.08644375
        },
        {
          "x": 23,
          "y": 0.08644375
        },
        {
          "x": 24,
          "y": 0.08644375
        },
        {
          "x": 25,
          "y": 0.08644375
        },
        {
          "x": 26,
          "y": 0.08644375
        },
        {
          "x": 27,
          "y": 0.08644375
        },
        {
          "x": 28,
          "y": 0.08644375
        },
        {
          "x": 29,
          "y": 0.08644375
        },
        {
          "x": 30,
          "y": 0.08644375
        },
        {
          "x": 31,
          "y": 0.08644375
        },
        {
          "x": 32,
          "y": 0.12468958333333333
        },
        {
          "x": 33,
          "y": 0.12468958333333333
        },
        {
          "x": 34,
          "y": 0.12468958333333333
        },
        {
          "x": 35,
          "y": 0.12468958333333333
        },
        {
          "x": 36,
          "y": 0.12468958333333333
        },
        {
          "x": 37,
          "y": 0.12468958333333333
        },
        {
          "x": 38,
          "y": 0.12468958333333333
        },
        {
          "x": 39,
          "y": 0.12468958333333333
        },
        {
          "x": 40,
          "y": 0.15881458333333331
        },
        {
          "x": 41,
          "y": 0.15881458333333331
        },
        {
          "x": 42,
          "y": 0.15881458333333331
        },
        {
          "x": 43,
          "y": 0.15881458333333331
        },
        {
          "x": 44,
          "y": 0.15881458333333331
        },
        {
          "x": 45,
          "y": 0.15881458333333331
        },
        {
          "x": 46,
          "y": 0.15881458333333331
        },
        {
          "x": 47,
          "y": 0.15881458333333331
        },
        {
          "x": 48,
          "y": 0.15881458333333331
        },
        {
          "x": 49,
          "y": 0.15881458333333331
        },
        {
          "x": 50,
          "y": 0.19471875
        },
        {
          "x": 51,
          "y": 0.19471875
        },
        {
          "x": 52,
          "y": 0.19471875
        },
        {
          "x": 53,
          "y": 0.19471875
        },
        {
          "x": 54,
          "y": 0.19471875
        },
        {
          "x": 55,
          "y": 0.19471875
        },
        {
          "x": 56,
          "y": 0.19471875
        },
        {
          "x": 57,
          "y": 0.19471875
        },
        {
          "x": 58,
          "y": 0.19471875
        },
        {
          "x": 59,
          "y": 0.19471875
        },
        {
          "x": 60,
          "y": 0.23392708333333334
        },
        {
          "x": 61,
          "y": 0.23392708333333334
        },
        {
          "x": 62,
          "y": 0.23392708333333334
        },
        {
          "x": 63,
          "y": 0.23392708333333334
        },
        {
          "x": 64,
          "y": 0.23392708333333334
        },
        {
          "x": 65,
          "y": 0.23392708333333334
        },
        {
          "x": 66,
          "y": 0.23392708333333334
        },
        {
          "x": 67,
          "y": 0.23392708333333334
        },
        {
          "x": 68,
          "y": 0.23392708333333334
        },
        {
          "x": 69,
          "y": 0.27030625
        },
        {
          "x": 70,
          "y": 0.27030625
        },
        {
          "x": 71,
          "y": 0.27030625
        },
        {
          "x": 72,
          "y": 0.27030625
        },
        {
          "x": 73,
          "y": 0.27030625
        },
        {
          "x": 74,
          "y": 0.27030625
        },
        {
          "x": 75,
          "y": 0.27030625
        },
        {
          "x": 76,
          "y": 0.27030625
        },
        {
          "x": 77,
          "y": 0.30378958333333334
        },
        {
          "x": 78,
          "y": 0.30378958333333334
        },
        {
          "x": 79,
          "y": 0.30378958333333334
        },
        {
          "x": 80,
          "y": 0.30378958333333334
        },
        {
          "x": 81,
          "y": 0.30378958333333334
        },
        {
          "x": 82,
          "y": 0.30378958333333334
        },
        {
          "x": 83,
          "y": 0.30378958333333334
        },
        {
          "x": 84,
          "y": 0.30378958333333334
        },
        {
          "x": 85,
          "y": 0.30378958333333334
        },
        {
          "x": 86,
          "y": 0.33574791666666665
        },
        {
          "x": 87,
          "y": 0.33574791666666665
        },
        {
          "x": 88,
          "y": 0.33574791666666665
        },
        {
          "x": 89,
          "y": 0.33574791666666665
        },
        {
          "x": 90,
          "y": 0.33574791666666665
        },
        {
          "x": 91,
          "y": 0.33574791666666665
        },
        {
          "x": 92,
          "y": 0.33574791666666665
        },
        {
          "x": 93,
          "y": 0.33574791666666665
        },
        {
          "x": 94,
          "y": 0.36735625
        },
        {
          "x": 95,
          "y": 0.36735625
        },
        {
          "x": 96,
          "y": 0.36735625
        },
        {
          "x": 97,
          "y": 0.36735625
        },
        {
          "x": 98,
          "y": 0.36735625
        },
        {
          "x": 99,
          "y": 0.36735625
        },
        {
          "x": 100,
          "y": 0.36735625
        },
        {
          "x": 101,
          "y": 0.36735625
        },
        {
          "x": 102,
          "y": 0.3990020833333333
        },
        {
          "x": 103,
          "y": 0.3990020833333333
        },
        {
          "x": 104,
          "y": 0.3990020833333333
        },
        {
          "x": 105,
          "y": 0.3990020833333333
        },
        {
          "x": 106,
          "y": 0.3990020833333333
        },
        {
          "x": 107,
          "y": 0.3990020833333333
        },
        {
          "x": 108,
          "y": 0.3990020833333333
        },
        {
          "x": 109,
          "y": 0.4293416666666666
        },
        {
          "x": 110,
          "y": 0.4293416666666666
        },
        {
          "x": 111,
          "y": 0.4293416666666666
        },
        {
          "x": 112,
          "y": 0.4293416666666666
        },
        {
          "x": 113,
          "y": 0.4293416666666666
        },
        {
          "x": 114,
          "y": 0.4293416666666666
        },
        {
          "x": 115,
          "y": 0.4293416666666666
        },
        {
          "x": 116,
          "y": 0.4293416666666666
        },
        {
          "x": 117,
          "y": 0.459375
        },
        {
          "x": 118,
          "y": 0.459375
        },
        {
          "x": 119,
          "y": 0.459375
        },
        {
          "x": 120,
          "y": 0.459375
        },
        {
          "x": 121,
          "y": 0.459375
        },
        {
          "x": 122,
          "y": 0.459375
        },
        {
          "x": 123,
          "y": 0.459375
        },
        {
          "x": 124,
          "y": 0.459375
        },
        {
          "x": 125,
          "y": 0.4893895833333333
        },
        {
          "x": 126,
          "y": 0.4893895833333333
        },
        {
          "x": 127,
          "y": 0.4893895833333333
        },
        {
          "x": 128,
          "y": 0.4893895833333333
        },
        {
          "x": 129,
          "y": 0.4893895833333333
        },
        {
          "x": 130,
          "y": 0.4893895833333333
        },
        {
          "x": 131,
          "y": 0.4893895833333333
        },
        {
          "x": 132,
          "y": 0.51818125
        },
        {
          "x": 133,
          "y": 0.51818125
        },
        {
          "x": 134,
          "y": 0.51818125
        },
        {
          "x": 135,
          "y": 0.51818125
        },
        {
          "x": 136,
          "y": 0.51818125
        },
        {
          "x": 137,
          "y": 0.51818125
        },
        {
          "x": 138,
          "y": 0.51818125
        },
        {
          "x": 139,
          "y": 0.54504375
        },
        {
          "x": 140,
          "y": 0.54504375
        },
        {
          "x": 141,
          "y": 0.54504375
        },
        {
          "x": 142,
          "y": 0.54504375
        },
        {
          "x": 143,
          "y": 0.54504375
        },
        {
          "x": 144,
          "y": 0.54504375
        },
        {
          "x": 145,
          "y": 0.5683958333333334
        },
        {
          "x": 146,
          "y": 0.5683958333333334
        },
        {
          "x": 147,
          "y": 0.5683958333333334
        },
        {
          "x": 148,
          "y": 0.5683958333333334
        },
        {
          "x": 149,
          "y": 0.5683958333333334
        },
        {
          "x": 150,
          "y": 0.5888750000000001
        },
        {
          "x": 151,
          "y": 0.5888750000000001
        },
        {
          "x": 152,
          "y": 0.5888750000000001
        },
        {
          "x": 153,
          "y": 0.5888750000000001
        },
        {
          "x": 154,
          "y": 0.5888750000000001
        },
        {
          "x": 155,
          "y": 0.6070250000000001
        },
        {
          "x": 156,
          "y": 0.6070250000000001
        },
        {
          "x": 157,
          "y": 0.6070250000000001
        },
        {
          "x": 158,
          "y": 0.6070250000000001
        },
        {
          "x": 159,
          "y": 0.6238312500000002
        },
        {
          "x": 160,
          "y": 0.6238312500000002
        },
        {
          "x": 161,
          "y": 0.6238312500000002
        },
        {
          "x": 162,
          "y": 0.6238312500000002
        },
        {
          "x": 163,
          "y": 0.6396687500000001
        },
        {
          "x": 164,
          "y": 0.6396687500000001
        },
        {
          "x": 165,
          "y": 0.6396687500000001
        },
        {
          "x": 166,
          "y": 0.6396687500000001
        },
        {
          "x": 167,
          "y": 0.6547875000000001
        },
        {
          "x": 168,
          "y": 0.6547875000000001
        },
        {
          "x": 169,
          "y": 0.6547875000000001
        },
        {
          "x": 170,
          "y": 0.6547875000000001
        },
        {
          "x": 171,
          "y": 0.6687083333333335
        },
        {
          "x": 172,
          "y": 0.6687083333333335
        },
        {
          "x": 173,
          "y": 0.6687083333333335
        },
        {
          "x": 174,
          "y": 0.6821208333333335
        },
        {
          "x": 175,
          "y": 0.6821208333333335
        },
        {
          "x": 176,
          "y": 0.6821208333333335
        },
        {
          "x": 177,
          "y": 0.6943125000000002
        },
        {
          "x": 178,
          "y": 0.6943125000000002
        },
        {
          "x": 179,
          "y": 0.6943125000000002
        },
        {
          "x": 180,
          "y": 0.7063104166666669
        },
        {
          "x": 181,
          "y": 0.7063104166666669
        },
        {
          "x": 182,
          "y": 0.7063104166666669
        },
        {
          "x": 183,
          "y": 0.717341666666667
        },
        {
          "x": 184,
          "y": 0.717341666666667
        },
        {
          "x": 185,
          "y": 0.717341666666667
        },
        {
          "x": 186,
          "y": 0.7279187500000003
        },
        {
          "x": 187,
          "y": 0.7279187500000003
        },
        {
          "x": 188,
          "y": 0.7378145833333336
        },
        {
          "x": 189,
          "y": 0.7378145833333336
        },
        {
          "x": 190,
          "y": 0.7378145833333336
        },
        {
          "x": 191,
          "y": 0.7471375000000002
        },
        {
          "x": 192,
          "y": 0.7471375000000002
        },
        {
          "x": 193,
          "y": 0.7560645833333336
        },
        {
          "x": 194,
          "y": 0.7560645833333336
        },
        {
          "x": 195,
          "y": 0.7645895833333336
        },
        {
          "x": 196,
          "y": 0.7645895833333336
        },
        {
          "x": 197,
          "y": 0.7729770833333336
        },
        {
          "x": 198,
          "y": 0.7729770833333336
        },
        {
          "x": 199,
          "y": 0.7807562500000003
        },
        {
          "x": 200,
          "y": 0.7807562500000003
        },
        {
          "x": 201,
          "y": 0.787997916666667
        },
        {
          "x": 202,
          "y": 0.787997916666667
        },
        {
          "x": 203,
          "y": 0.7950604166666669
        },
        {
          "x": 204,
          "y": 0.8013500000000002
        },
        {
          "x": 205,
          "y": 0.8013500000000002
        },
        {
          "x": 206,
          "y": 0.8075020833333335
        },
        {
          "x": 207,
          "y": 0.8132437500000002
        },
        {
          "x": 208,
          "y": 0.8132437500000002
        },
        {
          "x": 209,
          "y": 0.8187833333333335
        },
        {
          "x": 210,
          "y": 0.8241500000000002
        },
        {
          "x": 211,
          "y": 0.8292062500000001
        },
        {
          "x": 212,
          "y": 0.8292062500000001
        },
        {
          "x": 213,
          "y": 0.8341958333333335
        },
        {
          "x": 214,
          "y": 0.8390187500000001
        },
        {
          "x": 215,
          "y": 0.8437145833333335
        },
        {
          "x": 216,
          "y": 0.8481416666666668
        },
        {
          "x": 217,
          "y": 0.8522416666666668
        },
        {
          "x": 218,
          "y": 0.8561166666666667
        },
        {
          "x": 219,
          "y": 0.8598437500000001
        },
        {
          "x": 220,
          "y": 0.8636104166666668
        },
        {
          "x": 221,
          "y": 0.8671770833333335
        },
        {
          "x": 222,
          "y": 0.8706208333333335
        },
        {
          "x": 223,
          "y": 0.8739500000000002
        },
        {
          "x": 224,
          "y": 0.8801270833333336
        },
        {
          "x": 225,
          "y": 0.8830604166666669
        },
        {
          "x": 226,
          "y": 0.8859375000000003
        },
        {
          "x": 227,
          "y": 0.8912187500000003
        },
        {
          "x": 228,
          "y": 0.8958750000000003
        },
        {
          "x": 229,
          "y": 0.8980437500000004
        },
        {
          "x": 230,
          "y": 0.902122916666667
        },
        {
          "x": 231,
          "y": 0.9078020833333337
        },
        {
          "x": 232,
          "y": 0.9115145833333337
        },
        {
          "x": 233,
          "y": 0.9152770833333337
        },
        {
          "x": 234,
          "y": 0.9186208333333337
        },
        {
          "x": 235,
          "y": 0.9229833333333337
        },
        {
          "x": 236,
          "y": 0.9266458333333337
        },
        {
          "x": 237,
          "y": 0.9308687500000004
        },
        {
          "x": 238,
          "y": 0.9347437500000003
        },
        {
          "x": 239,
          "y": 0.9390083333333337
        },
        {
          "x": 240,
          "y": 0.942379166666667
        },
        {
          "x": 241,
          "y": 0.946597916666667
        },
        {
          "x": 242,
          "y": 0.9504437500000004
        },
        {
          "x": 243,
          "y": 0.9548937500000003
        },
        {
          "x": 244,
          "y": 0.9584937500000004
        },
        {
          "x": 245,
          "y": 0.962622916666667
        },
        {
          "x": 246,
          "y": 0.9662520833333337
        },
        {
          "x": 247,
          "y": 0.970147916666667
        },
        {
          "x": 248,
          "y": 0.973941666666667
        },
        {
          "x": 249,
          "y": 0.9783270833333337
        },
        {
          "x": 250,
          "y": 0.9816645833333337
        },
        {
          "x": 251,
          "y": 0.9861875000000004
        },
        {
          "x": 252,
          "y": 0.9901145833333338
        },
        {
          "x": 253,
          "y": 0.9939958333333337
        },
        {
          "x": 254,
          "y": 0.997991666666667
        },
        {
          "x": 255,
          "y": 1.0000000000000004
        }
      ]
    }
  ],
  "scales": [
    {
      "name": "wymulrjs-x-scale",
      "type": "linear",
      "domain": {
        "data": "wymulrjs",
        "field": "data.x"
      },
      "range": "width"
    },
    {
      "name": "wymulrjs-y-scale",
      "type": "linear",
      "domain": {
        "data": "wymulrjs",
        "field": "data.y"
      },
      "range": "height"
    }
  ],
  "marks": [
    {
      "type": "rect",
      "from": {
        "data": "wymulrjs"
      },
      "properties": {
        "enter": {
          "x": {
            "field": "data.x",
            "scale": "wymulrjs-x-scale"
          },
          "width": {
            "value": 0.9,
            "scale": "wymulrjs-x-scale"
          },
          "y": {
            "field": "data.y",
            "scale": "wymulrjs-y-scale"
          },
          "y2": {
            "value": 0,
            "scale": "wymulrjs-y-scale"
          }
        },
        "update": {
          "fill": {
            "value": "steelblue"
          }
        },
        "hover": {
          "fill": {
            "value": "limegreen"
          }
        }
      }
    },
    {
      "type": "line",
      "from": {
        "data": "maoyjwri"
      },
      "properties": {
        "enter": {
          "x": {
            "field": "data.x",
            "scale": "wymulrjs-x-scale"
          },
          "y": {
            "field": "data.y",
            "scale": "wymulrjs-y-scale"
          }
        },
        "update": {
          "stroke": {
            "value": "black"
          },
          "strokeWidth": {
            "value": 2
          }
        },
        "hover": {
          "stroke": {
            "value": "darkred"
          },
          "strokeWidth": {
            "value": 3
          }
        }
      }
    }
  ],
  "axes": [
    {
      "type": "x",
      "scale": "wymulrjs-x-scale"
    },
    {
      "type": "y",
      "scale": "wymulrjs-y-scale"
    }
  ]
}